src/__init__.py
src/chunker.py
src/main.py
src/models.py
src/parser.py
src/server.py
src/tools.py
diffchunk-0.1.5.dist-info/METADATA
diffchunk-0.1.5.dist-info/WHEEL
diffchunk-0.1.5.dist-info/entry_points.txt
diffchunk-0.1.5.dist-info/licenses/LICENSE
diffchunk-0.1.5.dist-info/RECORD
