Metadata-Version: 2.4
Name: diffchunk
Version: 0.1.5
Summary: MCP server for navigating large diff files with intelligent chunking
Project-URL: Homepage, https://github.com/peteretelej/diffchunk
Project-URL: Repository, https://github.com/peteretelej/diffchunk.git
Project-URL: Issues, https://github.com/peteretelej/diffchunk/issues
Project-URL: Documentation, https://github.com/peteretelej/diffchunk#readme
Author-email: Peter Etelej <peter@etelej.com>
Maintainer-email: Peter Etelej <peter@etelej.com>
License: MIT
License-File: LICENSE
Keywords: ai-tools,diff,llm,mcp,parsing
Classifier: Development Status :: 4 - Beta
Classifier: Intended Audience :: Developers
Classifier: Operating System :: OS Independent
Classifier: Programming Language :: Python :: 3
Classifier: Programming Language :: Python :: 3.10
Classifier: Programming Language :: Python :: 3.11
Classifier: Programming Language :: Python :: 3.12
Classifier: Topic :: Software Development :: Libraries :: Python Modules
Classifier: Topic :: Text Processing
Requires-Python: >=3.10
Requires-Dist: click>=8.2.1
Requires-Dist: mcp>=1.10.0
